bashbot_package/bashbot_index.py
bashbot_build-0.0.1.dist-info/METADATA
bashbot_build-0.0.1.dist-info/WHEEL
bashbot_build-0.0.1.dist-info/entry_points.txt
bashbot_build-0.0.1.dist-info/top_level.txt
bashbot_build-0.0.1.dist-info/RECORD
